asyncgTTS/__init__.py
asyncgTTS/_decos.py
asyncgTTS/asyncgTTS.py
asyncgTTS/easygTTS.py
asyncgTTS/errors.py
asyncgTTS/gtts.py
asyncgTTS-0.3.1.dist-info/LICENCE.txt
asyncgTTS-0.3.1.dist-info/METADATA
asyncgTTS-0.3.1.dist-info/WHEEL
asyncgTTS-0.3.1.dist-info/top_level.txt
asyncgTTS-0.3.1.dist-info/RECORD
