Metadata-Version: 2.1
Name: asyncgTTS
Version: 0.3.1
Summary: Async interfaces to the official Google Text to Speech or easygtts APIs
Home-page: https://github.com/gnome-py/asyncgTTS
Author: Gnome-py
Author-email: gnome6669.py@gmail.com
License: MIT
Download-URL: https://github.com/Gnome-py/asyncgTTS/archive/v0.3.0.tar.gz
Keywords: async,TTS,gtts,text to speech
Platform: UNKNOWN
Classifier: Intended Audience :: Developers
Classifier: License :: OSI Approved :: MIT License
Classifier: Programming Language :: Python :: 3
Classifier: Programming Language :: Python :: 3.6
Classifier: Programming Language :: Python :: 3.7
Classifier: Programming Language :: Python :: 3.8
Classifier: Programming Language :: Python :: 3.9
License-File: LICENCE.txt
Requires-Dist: aiohttp
Requires-Dist: pyJWT[crypto]
